nnViewer/__init__.py
nnViewer/back/__init__.py
nnViewer/back/graph.py
nnViewer/back/graph_initializer.py
nnViewer/back/hook_functions.py
nnViewer/back/models.py
nnViewer/back/node_getter.py
nnViewer/back/nodes.py
nnViewer/back/utils.py
nnViewer/back/wrapped_function.py
nnViewer/back/wrapper.py
nnViewer/front/__init__.py
nnViewer/front/gui.py
nnViewer/front/maps.py
nnViewer/front/node_item.py
nnViewer/front/utils.py
nnViewer-0.1.4.dist-info/METADATA
nnViewer-0.1.4.dist-info/WHEEL
nnViewer-0.1.4.dist-info/top_level.txt
nnViewer-0.1.4.dist-info/RECORD
