Metadata-Version: 2.2
Name: nnViewer
Version: 0.1.4
Summary: A neural network visualization tool
Home-page: https://github.com/PBDESG/nnViewer
Author: PBDESG
Author-email: PBDESG <pbdesg@gmail.com>
License: MIT
Keywords: neural networks,visualization,torch,PyQt5,graphviz
Requires-Python: >=3.6
Requires-Dist: torch
Requires-Dist: pygraphviz==1.14
Requires-Dist: PyQt5==5.15.11
Requires-Dist: graphviz
Requires-Dist: scipy
Provides-Extra: visualization
Requires-Dist: pygraphviz==1.14; extra == "visualization"
Dynamic: author
Dynamic: home-page
Dynamic: requires-python
